pyiron_continuum/__init__.py
pyiron_continuum/_version.py
pyiron_continuum/mesh.py
pyiron_continuum/project.py
pyiron_continuum/toolkit.py
pyiron_continuum/damask/__init__.py
pyiron_continuum/damask/damaskjob.py
pyiron_continuum/damask/factory.py
pyiron_continuum/damask/regrid.py
pyiron_continuum/elasticity/__init__.py
pyiron_continuum/elasticity/eshelby.py
pyiron_continuum/elasticity/green.py
pyiron_continuum/elasticity/linear_elasticity.py
pyiron_continuum/elasticity/tools.py
pyiron_continuum/fenics/__init__.py
pyiron_continuum/fenics/factory.py
pyiron_continuum/fenics/fix_plotting.py
pyiron_continuum/fenics/plot.py
pyiron_continuum/fenics/job/__init__.py
pyiron_continuum/fenics/job/elastic.py
pyiron_continuum/fenics/job/generic.py
pyiron_continuum/fenicsx/__init__.py
pyiron_continuum/fenicsx/factory.py
pyiron_continuum/fenicsx/plot.py
pyiron_continuum/fenicsx/job/__init__.py
pyiron_continuum/fenicsx/job/generic.py
pyiron_continuum/schroedinger/__init__.py
pyiron_continuum/schroedinger/potentials.py
pyiron_continuum/schroedinger/schroedinger.py
pyiron_continuum-0.0.10.dist-info/LICENSE
pyiron_continuum-0.0.10.dist-info/METADATA
pyiron_continuum-0.0.10.dist-info/WHEEL
pyiron_continuum-0.0.10.dist-info/top_level.txt
pyiron_continuum-0.0.10.dist-info/RECORD
