Metadata-Version: 2.1
Name: pyiron_continuum
Version: 0.0.10
Summary: Repository for user-generated plugins to the pyiron IDE.
Home-page: https://github.com/pyiron/pyiron_continuum
Author: Max-Planck-Institut für Eisenforschung GmbH - Computational Materials Design (CM) Department
Author-email: huber@mpie.de
License: BSD
Keywords: pyiron
Classifier: Development Status :: 4 - Beta
Classifier: Topic :: Scientific/Engineering :: Physics
Classifier: License :: OSI Approved :: BSD License
Classifier: Intended Audience :: Science/Research
Classifier: Operating System :: OS Independent
Classifier: Programming Language :: Python :: 3
Classifier: Programming Language :: Python :: 3.8
Classifier: Programming Language :: Python :: 3.9
Classifier: Programming Language :: Python :: 3.10
Classifier: Programming Language :: Python :: 3.11
License-File: LICENSE
Requires-Dist: matplotlib>=3.9.2
Requires-Dist: numpy>=1.26.4
Requires-Dist: pyiron_base>=0.9.12
Requires-Dist: pyiron_snippets>=0.1.4
Requires-Dist: scipy>=1.14.1
Requires-Dist: sympy>=1.13.2
Provides-Extra: fenics
Requires-Dist: fenics>=2019.1.0; extra == "fenics"
Requires-Dist: mshr>=2019.1.0; extra == "fenics"
Provides-Extra: schroedinger
Requires-Dist: k3d>=2.16.1; extra == "schroedinger"
